MANIFEST.in
README.md
license.txt
requirements.txt
setup.py
xlcocotools/Makefile
xlcocotools/__init__.py
xlcocotools/_mask.c
xlcocotools/_mask.pyx
xlcocotools/coco.py
xlcocotools/cocoeval.py
xlcocotools/mask.py
xlcocotools.egg-info/PKG-INFO
xlcocotools.egg-info/SOURCES.txt
xlcocotools.egg-info/dependency_links.txt
xlcocotools.egg-info/top_level.txt
xlcocotools/common/maskApi.c
xlcocotools/common/gason.cpp
xlcocotools/common/gason.h
xlcocotools/common/maskApi.c
xlcocotools/common/maskApi.h
xlcocotools/numpy_include/numpy/__multiarray_api.c
xlcocotools/numpy_include/numpy/__multiarray_api.h
xlcocotools/numpy_include/numpy/__ufunc_api.c
xlcocotools/numpy_include/numpy/__ufunc_api.h
xlcocotools/numpy_include/numpy/_neighborhood_iterator_imp.h
xlcocotools/numpy_include/numpy/_numpyconfig.h
xlcocotools/numpy_include/numpy/_public_dtype_api_table.h
xlcocotools/numpy_include/numpy/arrayobject.h
xlcocotools/numpy_include/numpy/arrayscalars.h
xlcocotools/numpy_include/numpy/dtype_api.h
xlcocotools/numpy_include/numpy/halffloat.h
xlcocotools/numpy_include/numpy/ndarrayobject.h
xlcocotools/numpy_include/numpy/ndarraytypes.h
xlcocotools/numpy_include/numpy/npy_1_7_deprecated_api.h
xlcocotools/numpy_include/numpy/npy_2_compat.h
xlcocotools/numpy_include/numpy/npy_2_complexcompat.h
xlcocotools/numpy_include/numpy/npy_3kcompat.h
xlcocotools/numpy_include/numpy/npy_common.h
xlcocotools/numpy_include/numpy/npy_cpu.h
xlcocotools/numpy_include/numpy/npy_endian.h
xlcocotools/numpy_include/numpy/npy_math.h
xlcocotools/numpy_include/numpy/npy_no_deprecated_api.h
xlcocotools/numpy_include/numpy/npy_os.h
xlcocotools/numpy_include/numpy/numpyconfig.h
xlcocotools/numpy_include/numpy/ufuncobject.h
xlcocotools/numpy_include/numpy/utils.h
xlcocotools/numpy_include/numpy/random/bitgen.h
xlcocotools/numpy_include/numpy/random/distributions.h
xlcocotools/numpy_include/numpy/random/libdivide.h