Metadata-Version: 2.1
Name: xlcocotools
Version: 0.0.9
Summary: pycocotools修改版本
Home-page: https://github.com/code4101/xlcocotools
Author: code4101
Author-email: 877362867@qq.com
Keywords: xlcocotools
Classifier: Programming Language :: Python :: 3
Classifier: Operating System :: OS Independent
Requires-Python: >=3.6
License-File: license.txt
